pakman/__init__.py
pakman/installer.py
pakman-0.2.0.dist-info/LICENSE
pakman-0.2.0.dist-info/METADATA
pakman-0.2.0.dist-info/WHEEL
pakman-0.2.0.dist-info/top_level.txt
pakman-0.2.0.dist-info/RECORD
